injectipy/__init__.py
injectipy/async_utils.py
injectipy/exceptions.py
injectipy/inject.py
injectipy/models/__init__.py
injectipy/models/inject.py
injectipy/py.typed
injectipy/scope.py
injectipy-0.3.0.dist-info/LICENSE
injectipy-0.3.0.dist-info/METADATA
injectipy-0.3.0.dist-info/WHEEL
injectipy-0.3.0.dist-info/RECORD
