Metadata-Version: 2.1
Name: injectipy
Version: 0.3.0
Summary: A dependency injection library for Python with async/await support using explicit scopes instead of global state
Home-page: https://github.com/Wimonder/injectipy
License: MIT
Keywords: dependency injection,async,asyncio,context manager,type safety
Author: Wim Onderbeke
Author-email: wim.onderbeke@hotmail.com
Requires-Python: >=3.11,<4.0
Classifier: License :: OSI Approved :: MIT License
Classifier: Programming Language :: Python :: 3
Classifier: Programming Language :: Python :: 3.11
Classifier: Programming Language :: Python :: 3.12
Classifier: Programming Language :: Python :: 3.13
Project-URL: Documentation, https://wimonder.github.io/injectipy/
Project-URL: Repository, https://github.com/Wimonder/injectipy
